cloudknot/__init__.py
cloudknot/_version.py
cloudknot/cli.py
cloudknot/cloudknot.py
cloudknot/config.py
cloudknot/dockerimage.py
cloudknot/aws/__init__.py
cloudknot/aws/base_classes.py
cloudknot/aws/batch.py
cloudknot/aws/ecr.py
cloudknot/commands/__init__.py
cloudknot/commands/base.py
cloudknot/commands/configure.py
cloudknot/data/config_ref_data/test_add_resource.cfg
cloudknot/data/config_ref_data/test_remove_resource.cfg
cloudknot/data/docker_image_ref_data/requirements.txt
cloudknot/data/docker_image_ref_data/ref1/Dockerfile
cloudknot/data/docker_image_ref_data/ref1/requirements.txt
cloudknot/data/docker_image_ref_data/ref1/script.py
cloudknot/data/docker_image_ref_data/ref2/Dockerfile
cloudknot/data/docker_image_ref_data/ref2/script.py
cloudknot/data/docker_reqs_ref_data/py3/ref1/Dockerfile
cloudknot/data/docker_reqs_ref_data/py3/ref1/requirements.txt
cloudknot/data/docker_reqs_ref_data/py3/ref1/unit-testing-func.py
cloudknot/data/docker_reqs_ref_data/py3/ref2/Dockerfile
cloudknot/data/docker_reqs_ref_data/py3/ref2/requirements.txt
cloudknot/data/docker_reqs_ref_data/py3/ref2/test-func-input.py
cloudknot/data/profiles_ref_data/cloudknot_with_profile
cloudknot/data/profiles_ref_data/cloudknot_without_profile
cloudknot/data/profiles_ref_data/config
cloudknot/data/profiles_ref_data/credentials_with_default
cloudknot/data/profiles_ref_data/credentials_without_default
cloudknot/templates/Dockerfile.template
cloudknot/templates/batch-environment-gpu-increase-ebs-volume.template
cloudknot/templates/batch-environment-gpu.template
cloudknot/templates/batch-environment-increase-ebs-volume.template
cloudknot/templates/batch-environment.template
cloudknot/templates/pars-with-default-vpc.template
cloudknot/templates/pars-with-new-vpc.template
cloudknot/templates/script.template
cloudknot/tests/__init__.py
cloudknot/tests/test_aws.py
cloudknot/tests/test_config.py
cloudknot/tests/test_docker_image.py
cloudknot/tests/test_knot.py
cloudknot/tests/test_pars.py
cloudknot-0.6.1.dist-info/LICENSE
cloudknot-0.6.1.dist-info/METADATA
cloudknot-0.6.1.dist-info/WHEEL
cloudknot-0.6.1.dist-info/entry_points.txt
cloudknot-0.6.1.dist-info/top_level.txt
cloudknot-0.6.1.dist-info/RECORD
