Metadata-Version: 2.1
Name: cloudknot
Version: 0.6.1
Summary: Cloudknot: a python library designed to run your existing python code on AWS Batch
Home-page: https://nrdg.github.io/cloudknot
Download-URL: https://github.com/nrdg/cloudknot
Author: Adam Richie-Halford
Author-email: richiehalford@gmail.com
Maintainer: Adam Richie-Halford
Maintainer-email: richiehalford@gmail.com
License: MIT
Platform: OS Independent
Classifier: Development Status :: 3 - Alpha
Classifier: Environment :: Console
Classifier: Intended Audience :: Science/Research
Classifier: License :: OSI Approved :: MIT License
Classifier: Operating System :: OS Independent
Classifier: Programming Language :: Python
Classifier: Topic :: Scientific/Engineering
Requires-Python: >=3.6
License-File: LICENSE
Requires-Dist: boto3 >=1.34.31
Requires-Dist: awscli >=1.32.31
Requires-Dist: botocore >=1.34.31
Requires-Dist: cloudpickle
Requires-Dist: docker >=3.0.0
Requires-Dist: pipreqs >=0.4.11
Requires-Dist: tenacity >=6.3.0
Provides-Extra: dev
Requires-Dist: black ==23.7.0 ; extra == 'dev'
Requires-Dist: coverage ==5.3 ; extra == 'dev'
Requires-Dist: flake8 ==3.8.3 ; extra == 'dev'
Requires-Dist: numpydoc ==1.1.0 ; extra == 'dev'
Requires-Dist: moto[cloudformation] ==4.1.5 ; extra == 'dev'
Requires-Dist: pre-commit ==3.3.3 ; extra == 'dev'
Requires-Dist: pydocstyle ==5.1.1 ; extra == 'dev'
Requires-Dist: pytest-cov ==2.10.1 ; extra == 'dev'
Requires-Dist: pytest-xdist[psutil] ==2.1.0 ; extra == 'dev'
Requires-Dist: pytest ==7.4.0 ; extra == 'dev'
Requires-Dist: sphinx ==5.0.0 ; extra == 'dev'
Provides-Extra: maint
Requires-Dist: rapidfuzz ==0.12.2 ; extra == 'maint'
